somfy_mylink_synergy/__init__.py
somfy_mylink_synergy-1.0.6.dist-info/LICENSE
somfy_mylink_synergy-1.0.6.dist-info/METADATA
somfy_mylink_synergy-1.0.6.dist-info/WHEEL
somfy_mylink_synergy-1.0.6.dist-info/top_level.txt
somfy_mylink_synergy-1.0.6.dist-info/RECORD
