Metadata-Version: 2.1
Name: somfy-mylink-synergy
Version: 1.0.6
Summary: Python API to utilise the Somfy Synergy JsonRPC API
Home-page: http://github.com/bendews/somfy-mylink-synergy
Author: Ben Dews
Author-email: contact@bendews.com
License: MIT
Keywords: somfy mylink synergy covers sensors api jsonrpc
Platform: any
